nvfuser/_C.cpython-310-x86_64-linux-gnu.so
nvfuser/__init__.py
nvfuser/__init__.pyi
nvfuser/nvfuser_version.py
nvfuser/pytorch_utils.py
nvfuser/utils.py
nvfuser/version.py
nvfuser/contrib/__init__.py
nvfuser/contrib/nn/__init__.py
nvfuser/contrib/nn/normalization.py
nvfuser/include/nvfuser/abstract_tensor.h
nvfuser/include/nvfuser/alias_analysis.h
nvfuser/include/nvfuser/bfs.h
nvfuser/include/nvfuser/codegen.h
nvfuser/include/nvfuser/compute_at.h
nvfuser/include/nvfuser/compute_at_map.h
nvfuser/include/nvfuser/contiguity.h
nvfuser/include/nvfuser/cuda_utils.h
nvfuser/include/nvfuser/debug.h
nvfuser/include/nvfuser/disjoint_set.h
nvfuser/include/nvfuser/dispatch.h
nvfuser/include/nvfuser/driver_api.h
nvfuser/include/nvfuser/dynamic_transform.h
nvfuser/include/nvfuser/evaluator_common.h
nvfuser/include/nvfuser/exceptions.h
nvfuser/include/nvfuser/executor.h
nvfuser/include/nvfuser/executor_kernel_arg.h
nvfuser/include/nvfuser/executor_params.h
nvfuser/include/nvfuser/executor_utils.h
nvfuser/include/nvfuser/expr_evaluator.h
nvfuser/include/nvfuser/expr_simplifier.h
nvfuser/include/nvfuser/fusion.h
nvfuser/include/nvfuser/fusion_profiler.h
nvfuser/include/nvfuser/fusion_segmenter.h
nvfuser/include/nvfuser/global_allocator.h
nvfuser/include/nvfuser/grouped_reduction.h
nvfuser/include/nvfuser/index_compute.h
nvfuser/include/nvfuser/inlining.h
nvfuser/include/nvfuser/instrumentation.h
nvfuser/include/nvfuser/iter_visitor.h
nvfuser/include/nvfuser/kernel.h
nvfuser/include/nvfuser/kernel_cache.h
nvfuser/include/nvfuser/kernel_ir.h
nvfuser/include/nvfuser/kernel_ir_dispatch.h
nvfuser/include/nvfuser/linked_hash_map.h
nvfuser/include/nvfuser/logical_domain_map.h
nvfuser/include/nvfuser/macros.h
nvfuser/include/nvfuser/maxinfo_propagator.h
nvfuser/include/nvfuser/mma_type.h
nvfuser/include/nvfuser/non_divisible_split.h
nvfuser/include/nvfuser/opaque_type.h
nvfuser/include/nvfuser/options.h
nvfuser_cu118_torch24-0.2.9.dev20240808.dist-info/LICENSE
nvfuser_cu118_torch24-0.2.9.dev20240808.dist-info/METADATA
nvfuser_cu118_torch24-0.2.9.dev20240808.dist-info/WHEEL
nvfuser_cu118_torch24-0.2.9.dev20240808.dist-info/top_level.txt
nvfuser_cu118_torch24-0.2.9.dev20240808.dist-info/RECORD
